odoo/addons/sale_loyalty_order_line_link/README.rst
odoo/addons/sale_loyalty_order_line_link/__init__.py
odoo/addons/sale_loyalty_order_line_link/__manifest__.py
odoo/addons/sale_loyalty_order_line_link/i18n/es.po
odoo/addons/sale_loyalty_order_line_link/i18n/it.po
odoo/addons/sale_loyalty_order_line_link/i18n/sale_coupon_order_line_link.pot
odoo/addons/sale_loyalty_order_line_link/i18n/sale_loyalty_order_line_link.pot
odoo/addons/sale_loyalty_order_line_link/models/__init__.py
odoo/addons/sale_loyalty_order_line_link/models/loyalty_program.py
odoo/addons/sale_loyalty_order_line_link/models/sale_order.py
odoo/addons/sale_loyalty_order_line_link/readme/CONTRIBUTORS.md
odoo/addons/sale_loyalty_order_line_link/readme/DESCRIPTION.md
odoo/addons/sale_loyalty_order_line_link/readme/ROADMAP.md
odoo/addons/sale_loyalty_order_line_link/reports/__init__.py
odoo/addons/sale_loyalty_order_line_link/reports/sale_report.py
odoo/addons/sale_loyalty_order_line_link/reports/sale_report_views.xml
odoo/addons/sale_loyalty_order_line_link/static/description/icon.png
odoo/addons/sale_loyalty_order_line_link/static/description/index.html
odoo/addons/sale_loyalty_order_line_link/tests/__init__.py
odoo/addons/sale_loyalty_order_line_link/tests/test_sale_loyalty_order_line_link.py
odoo/addons/sale_loyalty_order_line_link/views/loyalty_program_views.xml
odoo/addons/sale_loyalty_order_line_link/views/sale_order_views.xml
odoo_addon_sale_loyalty_order_line_link-18.0.1.0.0.2.dist-info/METADATA
odoo_addon_sale_loyalty_order_line_link-18.0.1.0.0.2.dist-info/WHEEL
odoo_addon_sale_loyalty_order_line_link-18.0.1.0.0.2.dist-info/top_level.txt
odoo_addon_sale_loyalty_order_line_link-18.0.1.0.0.2.dist-info/RECORD
